my_package/__init__.py
priya_dharshni_2002-0.1.0.dist-info/licenses/license
priya_dharshni_2002-0.1.0.dist-info/METADATA
priya_dharshni_2002-0.1.0.dist-info/WHEEL
priya_dharshni_2002-0.1.0.dist-info/top_level.txt
priya_dharshni_2002-0.1.0.dist-info/RECORD
