Metadata-Version: 2.4
Name: Priya_dharshni_2002
Version: 0.1.0
Summary: A simple Python package that says hello
Author: Your Name
Author-email: priyadharshniramesh@gmail.com
Classifier: Programming Language :: Python :: 3
Classifier: License :: OSI Approved :: MIT License
Classifier: Operating System :: OS Independent
Requires-Python: >=3.6
License-File: license
Dynamic: author
Dynamic: author-email
Dynamic: classifier
Dynamic: license-file
Dynamic: requires-python
Dynamic: summary
